{"msg": "", "result": {"data": [{"sec_timing": false, "test_time": "1800", "test_free": false, "test_name": "Application of Derivatives Test - 3", "disable_partial_marking": false, "sec_details": [{"shuffling": true, "sec_id": "172d3ec210f3488ab387fea2a4d363a0", "sec_name": {"1": "Section -1"}, "sec_questions": [{"order_sign": [0, 0], "qid": "115ae5df10754a8eb1d59672cc66ba3b", "qtmpl": 1, "qd_id": "1", "neg_marks": 0, "que": {"1": {"q_option": ["<p>\\(x+12 y+158=0\\)</p>", "<p>\\(x-12 y-156=0\\)</p>", "<p>\\(12 x+y-156=0\\)</p>", "<p>\\(x+12 y-158=0\\)</p>"], "q_string": "<p>Find the equation of the normal to the curve \\(y=3 x^2+1\\), which passes through \\((2,13)\\)</p>"}}, "max_marks": 1}, {"order_sign": [1, 1], "qid": "25e675b7c27c4b4ab869bcb76d182582", "qtmpl": 1, "qd_id": "1", "neg_marks": 0, "que": {"1": {"q_option": ["<p>\\(\\frac{6 x^2-3}{6 y^2+3}\\)</p>", "<p>\\(\\frac{6 x^2-3}{6 y^2-3}\\)</p>", "<p>\\(\\frac{6 y^2-3}{6 x^2-3}\\)</p>", "<p>\\(\\frac{6 y^2+3}{6 x^2-3}\\)</p>"], "q_string": "<p>Find slope of the tangent to the curve \\(2 x^3+3 y=2 y^3+3 x\\) at \\(p(x, y)\\)</p>"}}, "max_marks": 1}, {"order_sign": [2, 2], "qid": "de88835e7ea64a7ba104b4008fe0413f", "qtmpl": 1, "qd_id": "0", "neg_marks": 0, "que": {"1": {"q_option": ["<p>\\(\\frac{d y}{d x}=0\\)</p>", "<p>\\(\\frac{d y}{d x}=1\\)</p>", "<p>\\(\\frac{d x}{d y}=0\\)</p><br/>", "<p>\\(\\frac{d x}{d y}=1\\)</p>"], "q_string": "<p>The normal to a given curve is parallel to \\(x\\)-axis if:</p>"}}, "max_marks": 1}, {"order_sign": [3, 3], "qid": "f6beb881948d4597ae63c6404f66d5ac", "qtmpl": 1, "qd_id": "1", "neg_marks": 0, "que": {"1": {"q_option": ["<p>\\(\\frac{\\pi } 6\\)</p>", "<p>\\(\\frac{\\pi } 4\\)</p>", "<p>\\(\\frac{3 \\pi }4\\)</p>", "<p>\\(\\frac{-\\pi} 4\\)</p>"], "q_string": "<p>Let the slope of the curve \\(y=\\sin ^{-1}(\\cos x)\\) be \\(\\tan \\theta\\), then the value of \\(\\theta\\) in the interval \\((0, \\pi)\\) is:</p>"}}, "max_marks": 1}, {"order_sign": [4, 4], "qid": "f9d81520662541b29cf39063f8b62eb0", "qtmpl": 1, "qd_id": "1", "neg_marks": 0, "que": {"1": {"q_option": ["<p>\\(\\frac{1}{\\sqrt{5}}\\)</p>", "<p>\\(\\frac{2}{\\sqrt{5}}\\)</p>", "<p>\\(\\frac{3}{\\sqrt{5}}\\)</p>", "<p>\\(\\frac{4}{\\sqrt{5}}\\)</p>"], "q_string": "<p>The tangent to the curve \\(y^{2}=16 x\\) and touches the curve at a point (1,4). Find the distance of origin from the tangent.<br/></p>"}}, "max_marks": 1}, {"order_sign": [5, 5], "qid": "e32483324b204e2c96f4a632f1bb5b64", "qtmpl": 1, "qd_id": "1", "neg_marks": 0, "que": {"1": {"q_option": ["<p>\\(y=2 x+2 \\pi\\)</p>", "<p>\\(y=2 x\\)</p>", "<p>\\(y=-2 x+2 \\pi\\)</p>", "<p>\\(y=-2 x\\)</p>"], "q_string": "<p>The equation of the tangent line to the curve \\(y=2 x \\sin x\\) at the point \\(\\left(\\frac{\\pi}{2}, \\pi\\right)\\) is:</p>"}}, "max_marks": 1}, {"order_sign": [7, 7], "qid": "4b364115465241798eaa18dd1ec536ee", "qtmpl": 1, "qd_id": "1", "neg_marks": 0, "que": {"1": {"q_option": ["<p>\\((3,3)\\)</p>", "<p>\\((3,2)\\)</p>", "<p>\\((2,3)\\)</p>", "<p>\\((2,2)\\)</p>"], "q_string": "<p>Find the point at which the tangent to the curve \\(y=\\sqrt{4 x -3}-1\\) has its slope \\(\\frac{2}{3}\\).</p>"}}, "max_marks": 1}, {"order_sign": [9, 9], "qid": "563c187a595640369f32b56c1844e7f9", "qtmpl": 1, "qd_id": "1", "neg_marks": 0, "que": {"1": {"q_option": ["<p>\\(\\frac{1 }{ 7}\\)</p>", "<p>\\(\\frac{4 }{ 7}\\)</p>", "<p>\\(\\frac{3 }{ 7}\\)</p>", "<p>\\(\\frac{6 }{ 7}\\)</p>"], "q_string": "<p>What is the slope of the tangent to the curve \\(x = t ^2+3 t -8, y =2 t ^2-2 t -5\\) at \\(t =2 ?\\)</p>"}}, "max_marks": 1}, {"order_sign": [10, 10], "qid": "c2e8f9cb0e12420d9559d3919182d723", "qtmpl": 1, "qd_id": "1", "neg_marks": 0, "que": {"1": {"q_option": ["<p>\\(y=2 x-1\\)</p>", "<p>\\(y=2 x+1\\)</p>", "<p>\\(y=x-1\\)</p>", "<p>\\(y=x+1\\)</p>"], "q_string": "<p>Find the equation of tangent of \\(y=x^2\\) at \\(x=1\\)</p>"}}, "max_marks": 1}, {"order_sign": [11, 11], "qid": "bf6752f76e41461a803d2abad3c64c97", "qtmpl": 1, "qd_id": "2", "neg_marks": 0, "que": {"1": {"q_option": ["<p>\\(2 \\sqrt{\u00a0 2} x+3 y+2=0\\)</p>", "<p>\\(2 \\sqrt{\u00a0 2} x-3 y+2=0\\)</p>", "<p>\\(2 \\sqrt{\u00a0 2} x-3 y-2=0\\)</p>", "<p>\\(2 \\sqrt{\u00a0 2} x+3 y-2=0\\)</p>"], "q_string": "<p>Find the equation of tangent to the curve \\(x=\\sin 3 t, y=\\cos 2 t\\) at \\(t=\\frac {\\pi } 4\\) ?</p>"}}, "max_marks": 1}, {"order_sign": [12, 12], "qid": "682a2a691f57492f91882b5cb6522fa2", "qtmpl": 1, "qd_id": "1", "neg_marks": 0, "que": {"1": {"q_option": ["<p>\\(80 x-40 y+103=0\\)</p>", "<p>\\(80 x+40 y+103=0\\)</p>", "<p>\\(80 x+40 y-103=0\\)</p>", "<p>\\(80 x-40 y-103=0\\)</p>"], "q_string": "<p>Find the equation of tangent to the curve \\(y=\\sqrt{5 x-3}-2\\), which is parallel to the line \\(4 x-2 y+3=0\\) ?</p>"}}, "max_marks": 1}, {"order_sign": [13, 13], "qid": "b73dd123e8154196a3a2e1ad7ead7bce", "qtmpl": 1, "qd_id": "1", "neg_marks": 0, "que": {"1": {"q_option": ["<p>\\(\\frac{1}{4}\\)</p>", "<p>\\(\\frac{1}{3}\\)</p>", "<p>\\(\\frac{1}{5}\\)</p>", "<p>None of the above</p>"], "q_string": "<p>Find the slope of the tangent to the curve \\(x y^2-2 x=4\\) at \\(x=2\\)</p>"}}, "max_marks": 1}, {"order_sign": [14, 14], "qid": "6f8831a8c51946c99697dd7e54e319d0", "qtmpl": 1, "qd_id": "1", "neg_marks": 0, "que": {"1": {"q_option": ["<p>\\((0,1)\\) and \\((2,4)\\)</p>", "<p>\\((0,0)\\) and \\((2,4)\\)</p>", "<p>\\((0,0)\\) and \\((3,4)\\)</p>", "<p>\\((0,0)\\) and \\((2,3)\\)</p>"], "q_string": "<p>Find the points on the curve \\(y=x^2\\) at which the slope of the tangent is equal to the \\(y\\)-coordinate of the point.</p>"}}, "max_marks": 1}, {"order_sign": [15, 15], "qid": "b260472d7a6547f99439249b1bdfe484", "qtmpl": 1, "qd_id": "2", "neg_marks": 0, "que": {"1": {"q_option": ["<p>\\(16 \\pi\\) m\\(^{2}/\\)sec</p>", "<p>\\(0.16 \\pi\\) m\\(^{2}/\\)sec</p>", "<p>\\(0.08 \\pi\\) m\\(^{2}/\\)sec</p>", "<p>\\(0.04 \\pi\\) m\\(^{2}/\\)sec</p>"], "q_string": "<p>The radius of a circle is changing at the rate of \\(\\frac{ dr }{ dt }=0.01\\) m/sec. The rate of change of its area \\(\\frac{ dA }{ dt }\\), when the radius of the circle is \\(4\\) m, is:</p>"}}, "max_marks": 1}, {"order_sign": [16, 16], "qid": "5095c2a7a93547edbd4ccb8b9918977d", "qtmpl": 1, "qd_id": "1", "neg_marks": 0, "que": {"1": {"q_option": ["<p>\\(184 \\pi\\)</p>", "<p>\\(196 \\pi\\)</p>", "<p>\\(195 \\pi\\)</p>", "<p>\\(194 \\pi\\)</p>"], "q_string": "<p>The rate of change of volume of a sphere with respect to its radius which is \\(7 cm\\) is:</p>"}}, "max_marks": 1}, {"order_sign": [17, 17], "qid": "57a0f31d34524cb8b06bf37294a92bcf", "qtmpl": 1, "qd_id": "1", "neg_marks": 0, "que": {"1": {"q_option": ["<p>3</p>", "<p>2</p>", "<p>1</p>", "<p>4</p>"], "q_string": "<p>The rate of change of surface area of the cube is \\(108 cm ^2 / s\\), find the length of the side at the moment if the sides varies at the rate \\(3 cm / s\\).</p>"}}, "max_marks": 1}, {"order_sign": [18, 18], "qid": "abe477e07fec4edf9d3e00265eef1413", "qtmpl": 1, "qd_id": "2", "neg_marks": 0, "que": {"1": {"q_option": ["<p>\\(24 cm ^2 / s\\)</p>", "<p>\\(32 cm ^2 / s\\)</p>", "<p>\\(36 cm ^2 / s\\)</p>", "<p>\\(48 cm ^2 / s\\)</p>"], "q_string": "<p>Find the rate of change of area of the square at the edge length of \\(12 cm\\), if the rate of change of edge length of the square is \\(2 cm / s\\).</p>"}}, "max_marks": 1}, {"order_sign": [19, 19], "qid": "26e5d393bac4452e9570a01bcef1f750", "qtmpl": 1, "qd_id": "2", "neg_marks": 0, "que": {"1": {"q_option": ["<p>\\(12 \\pi R^3\\)</p>", "<p>\\(4 \\pi R^2\\)</p>", "<p>\\(3 \\pi R^2\\)</p>", "<p>\\(12 \\pi R^2\\)</p>"], "q_string": "<p>A balloon, which always remains spherical, has a variable diameter \\(\\frac{3}{2}(4 x +3)\\). Find the rate of change of its volume with respect to \\(x\\).</p>"}}, "max_marks": 1}, {"order_sign": [20, 20], "qid": "8ee0248d2a234f9f96b452014009cc2c", "qtmpl": 1, "qd_id": "1", "neg_marks": 0, "que": {"1": {"q_option": ["<p>\\(10 cm ^2 / sec\\).</p>", "<p>\\(\\sqrt{3} cm ^2 / sec\\).</p>", "<p>\\(10 \\sqrt{3} cm ^2 / sec\\).</p>", "<p>\\(\\frac{10}{3} cm ^2 / sec\\).</p>"], "q_string": "<p>The sides of an equilateral triangle are increasing at the rate of \\(2 cm / sec\\). The rate at which the area increases, when side is \\(10 cm\\), is:</p>"}}, "max_marks": 1}, {"order_sign": [21, 21], "qid": "800572734ff349f99ea05355b29258fa", "qtmpl": 1, "qd_id": "2", "neg_marks": 0, "que": {"1": {"q_option": ["<p>Increasing, at 6 units/sec</p>", "<p>Increasing, at 3 units/sec</p>", "<p>decreasing, at 3 units/sec</p>", "<p>decreasing, at 6 units/sec</p>"], "q_string": "<p>For the given curve: \\(y=2 x-x^2\\), when \\(x\\) increases at the rate of 3 units \\(/ sec\\), then how the slope of curve changes?</p>"}}, "max_marks": 1}, {"order_sign": [22, 22], "qid": "d6b40f24a5e543bc9d4bf240f8214669", "qtmpl": 1, "qd_id": "1", "neg_marks": 0, "que": {"1": {"q_option": ["<p>\\(40 \\pi cm ^2 s ^{-1}\\)</p>", "<p>\\(80 \\pi cm ^2 s ^{-1}\\)</p>", "<p>\\(60 \\pi cm ^2 s ^{-1}\\)</p>", "<p>None of these</p>"], "q_string": "<p>A stone is dropped in a quiet lake and waves move in circles at the speed of \\(5 cm\\) \\(s ^{-1}\\). At the instant when the radius of the circular wave is \\(8 cm\\), how fast is the enclosed area increasing?</p>"}}, "max_marks": 1}, {"order_sign": [23, 23], "qid": "aa4160b996994a78a4db27e2da2bc237", "qtmpl": 1, "qd_id": "1", "neg_marks": 0, "que": {"1": {"q_option": ["<p>\\(\\frac{4}{3} \\pi cm ^2 / sec\\)</p>", "<p>\\(\\frac{2}{3} \\pi cm ^2 / sec\\)</p>", "<p>\\(4 \\pi cm ^2 / sec\\)</p>", "<p>\\(2 \\pi cm ^2 / sec\\)</p>"], "q_string": "<p>If the volume of spherical ball is increasing at the rate of \\(4 \\pi cc / sec\\) then the rate of change of its surface area when the volume is \\(288 \\pi \\) cc is:</p>"}}, "max_marks": 1}, {"order_sign": [24, 24], "qid": "336e1b5c649042d382797f2862697105", "qtmpl": 1, "qd_id": "1", "neg_marks": 0, "que": {"1": {"q_option": ["<p>\\(2 kmph\\), decreases</p>", "<p>\\(2 kmph\\) increases</p>", "<p>\\(4.5 kmph\\), increases</p>", "<p>\\(4.5 kmph\\) decreases</p>"], "q_string": "<p>A man of height 6 feet walks at uniform rate of \\(3 kmph\\) away from the lamp post of 15 feet height. The rate at which the length of his shadow changes is:</p>"}}, "max_marks": 1}, {"order_sign": [25, 25], "qid": "9cf9c44f57dd4a319f06289c18fe1392", "qtmpl": 1, "qd_id": "1", "neg_marks": 0, "que": {"1": {"q_option": ["<p>\\(\\frac{1 }{ 10}\\)</p>", "<p>\\(\\frac{1 }{ 20}\\)</p>", "<p>\\(\\frac{1 }{ 5}\\)</p>", "<p>None of these</p>"], "q_string": "<p>What is the rate of change of \\(\\sqrt{ x ^2+16}\\) with respect to \\(x ^2\\) at \\(x =3\\)?</p>"}}, "max_marks": 1}, {"order_sign": [26, 26], "qid": "19628f01922049868c27ab6472b48e34", "qtmpl": 1, "qd_id": "1", "neg_marks": 0, "que": {"1": {"q_option": ["<p>\\(80 m ^3 / s\\)</p>", "<p>\\(144 \\pi m ^3 / s\\)</p>", "<p>\\(144 \\pi m ^3 / s\\)</p>", "<p>\\(80 \\pi m ^3 / s\\)</p>"], "q_string": "<p>The radius of a cylinder is increasing at the rate of \\(3 m / s\\) and its altitude is decreasing at the rate of \\(4 m / s\\). The rate of change of volume when radius is \\(4 m\\) and altitude is \\(6 m\\) is:</p>"}}, "max_marks": 1}, {"order_sign": [27, 27], "qid": "7dbe52a419d84abb884e7a21550d170c", "qtmpl": 1, "qd_id": "1", "neg_marks": 0, "que": {"1": {"q_option": ["<p>80</p>", "<p>54</p>", "<p>24</p>", "<p>4</p>"], "q_string": "<p>The length \\(x\\) of a rectangle is decreasing at the rate of \\(7 cm / min\\) and the width \\(y\\) is increasing at the rate of \\(6 cm / min\\). when \\(x=10 cm\\) and \\(y=8 cm\\) find the rate of change of the area of the rectangle.</p>"}}, "max_marks": 1}, {"order_sign": [28, 28], "qid": "062ade1d5dfd4a18be34ad317245b10e", "qtmpl": 1, "qd_id": "1", "neg_marks": 0, "que": {"1": {"q_option": ["<p>1</p>", "<p>2</p>", "<p>3</p>", "<p>4</p>"], "q_string": "<p>The rate of change of volume of a sphere with respect to its surface area when the radius is \\(4 m\\) is</p>"}}, "max_marks": 1}, {"order_sign": [29, 29], "qid": "6005a8980ad640b39146c8352ad5222c", "qtmpl": 1, "qd_id": "1", "neg_marks": 0, "que": {"1": {"q_option": ["<p>\\(\\frac{1}{2} S \\frac{d r}{d t}\\)</p>", "<p>\\(\\frac{1}{2} r \\frac{d S}{d t}\\)</p>", "<p>\\(r \\frac{d S}{d t}\\)</p>", "<p>\\(\\frac{1}{2} r^2 \\frac{d S}{d t}\\)</p>"], "q_string": "<p>If at any instant \\(t\\), for a sphere, \\(r\\) denotes the radius, \\(S\\) denotes the surface area and \\(V\\) denotes the volume, then what is \\(\\frac{d V}{d t}\\) equal to?</p>"}}, "max_marks": 1}, {"order_sign": [30, 30], "qid": "4ce39f54c33541299721dc4baab38bc9", "qtmpl": 1, "qd_id": "1", "neg_marks": 0, "que": {"1": {"q_option": ["<p>\\(10 \\pi\\)</p>", "<p>\\(100 \\pi\\)</p>", "<p>\\(200 \\pi\\)</p>", "<p>\\(50 \\pi\\)</p>"], "q_string": "<p>A spherical balloon is expanding. If the radius is increasing at the rate of 2 centimeters per minute, the rate at which the volume increases (in cubic centimeters per minute) when the radius is 5 centimetres is:</p>"}}, "max_marks": 1}, {"order_sign": [31, 31], "qid": "9e9424f6798d4ae49716d2de4667f24e", "qtmpl": 1, "qd_id": "1", "neg_marks": 0, "que": {"1": {"q_option": ["<p>\\(18 \\sqrt{6}-\\frac{33}{2}\\)</p>", "<p>\\(12 \\sqrt{6}-\\frac{33}{2}\\)</p>", "<p>\\(12 \\sqrt{6}-\\frac{31}{2}\\)</p>", "<p>\\(18 \\sqrt{6}-\\frac{31}{2}\\)</p>"], "q_string": "<p>Let \\(x=2\\) be a local minima of the function \\(f(x)=2 x^4-18 x^2+8 x+12, x \\in(-4,4)\\) If \\(M\\) is local maximum value of the function \\(f\\) in \\((-4,4)\\), then \\(M=\\)?</p>"}}, "max_marks": 1}]}], "test_id": 190524, "optional_que_in_sec": false}, {"172d3ec210f3488ab387fea2a4d363a0": {"dist_neg": [[1, 30, 0]], "slug_pos": [1], "dist_pos": [[1, 30, 1]], "slug_neg": [0], "q_count": 30, "max_marks": 30}}, ["1"]], "user": {"name": "Admin", "level": 4}}, "code": 200, "status": true}